{
  "intro": "Miso is a fermented soybean paste that has been a cornerstone of Japanese cuisine for over a thousand years. At Mitsukabose, we carefully select and blend different types of miso to create our unique flavor profile.",
  "types": [
    {
      "id": "kaachan",
      "name": "Kaachan Miso",
      "origin": "Toyono Town",
      "flavor": "Rich, slightly sweet"
    },
    {
      "id": "marusan",
      "name": "Marusan Miso",
      "origin": "Nagano",
      "flavor": "Deep umami"
    },
    {
      "id": "ishino",
      "name": "Ishino White Miso",
      "origin": "Kyoto",
      "flavor": "Mild, creamy"
    },
    {
      "id": "yamago",
      "name": "Yamago Miso",
      "origin": "Yamanashi",
      "flavor": "Balanced sweetness"
    },
    {
      "id": "hozan",
      "name": "Hozan Miso",
      "origin": "Aichi",
      "flavor": "Full-bodied"
    },
    {
      "id": "kanto",
      "name": "Kantoya Miso",
      "origin": "Tokyo area",
      "flavor": "Earthy, robust"
    }
  ]
} 